eopf/__init__.py
eopf/py.typed
eopf/accessor/__init__.py
eopf/accessor/abstract.py
eopf/accessor/accessor_factory.py
eopf/accessor/attribute_to_flag_var.py
eopf/accessor/conveniences.py
eopf/accessor/filename_to_variable.py
eopf/accessor/grib.py
eopf/accessor/memmap_accessors.py
eopf/accessor/memmap_accessors_impl.py
eopf/accessor/netcdf_accessors.py
eopf/accessor/rasterio.py
eopf/accessor/xml_accessors.py
eopf/accessor/zarr.py
eopf/cli/__init__.py
eopf/cli/cli.py
eopf/cli/cli_convert.py
eopf/cli/cli_merge.py
eopf/cli/cli_model.py
eopf/cli/cli_qualitycontrol_triggers.py
eopf/cli/cli_triggering_triggers.py
eopf/cli/cli_validate.py
eopf/cli/merge_l0_safe_manifests.py
eopf/cli/services/__init__.py
eopf/cli/services/kafka_server.py
eopf/cli/services/web_server.py
eopf/common/__init__.py
eopf/common/constants.py
eopf/common/date_utils.py
eopf/common/dtree_utils.py
eopf/common/env_utils.py
eopf/common/file_utils.py
eopf/common/functions_utils.py
eopf/common/geometry_utils.py
eopf/common/history_utils.py
eopf/common/json_utils.py
eopf/common/numpy_utils.py
eopf/common/path_utils.py
eopf/common/pydantic_helpers.py
eopf/common/temp_utils.py
eopf/common/type_utils.py
eopf/common/xml_utils.py
eopf/computing/__init__.py
eopf/computing/abstract.py
eopf/computing/breakpoint.py
eopf/computing/merge.py
eopf/computing/merge_attributes.py
eopf/computing/merge_attributes_utils.py
eopf/computing/overlap.py
eopf/computing/py.typed
eopf/computing/utils.py
eopf/computing/validation.py
eopf/computing/tasktables/nominal.json
eopf/computing/tasktables/passthrought.json
eopf/config/__init__.py
eopf/config/config.py
eopf/config/default/eopf.toml
eopf/dask_utils/__init__.py
eopf/dask_utils/auto_gc_plugin.py
eopf/dask_utils/dask_cluster_monitor.py
eopf/dask_utils/dask_cluster_type.py
eopf/dask_utils/dask_context_manager.py
eopf/dask_utils/dask_context_utils.py
eopf/dask_utils/dask_helpers.py
eopf/dask_utils/dask_logging.py
eopf/dask_utils/failure_monitor_plugin.py
eopf/dask_utils/profiler.py
eopf-2.6.4.dist-info/entry_points.txt
eopf-2.6.4.dist-info/licenses/LICENSE
eopf-2.6.4.dist-info/WHEEL
eopf-2.6.4.dist-info/METADATA
eopf-2.6.4.dist-info/RECORD
